{
  "$schema": "https://raw.githubusercontent.com/googleapis/release-please/main/schemas/config.json",
  "release-type": "node",
  "bump-minor-pre-major": true,
  "bump-patch-for-minor-pre-major": true,
  "changelog-sections": [
    { "type": "feat", "section": "### Added", "hidden": false },
    { "type": "fix", "section": "### Fixed", "hidden": false },
    { "type": "security", "section": "### Security", "hidden": false },
    { "type": "perf", "section": "### Performance", "hidden": false },
    { "type": "docs", "section": "### Documentation", "hidden": false },
    { "type": "refactor", "section": "### Changed", "hidden": false },
    { "type": "chore", "section": "### Maintenance", "hidden": true },
    { "type": "test", "section": "### Tests", "hidden": true }
  ],
  "packages": {
    ".": {
      "changelog-path": "CHANGELOG.md",
      "release-type": "node",
      "include-component-in-tag": false,
      "extra-files": [
        "packages/ai-attribution-lint/package.json",
        "packages/ai-citation-sdk/package.json",
        "packages/crawl-manifest-client/package.json",
        "packages/aac-server/package.json",
        "packages/aac-dashboard-lite/package.json",
        "packages/vwp-gateway/package.json",
        "packages/referrer-middleware/package.json",
        "packages/honeypot-verifier/package.json",
        "packages/attribution-test-harness/package.json"
      ]
    }
  }
}
